{
  "name": "Shaving Trio (Bundle)",
  "slug": "ultimate-grooming-elegance-trio",
  "collection": "Bundles",
  "size": "Trio",
  "price": 67,
  "description": "The Ultimate Grooming Elegance Trio — Beard Oil, Beard & Shave Balm, and Hair & Beard Nourishment. A complete package for the modern man who values style and substance. (Was $119.)",
  "howToUse": null,
  "ingredients": "Combined ingredients of Beard Oil, Beard & Shave Balm, and Hair & Beard Nourishment.",
  "imageUrl": "https://mdrnclassic.com/cdn/shop/files/Untitleddesign_21.png?v=1708686296&width=600",
  "productUrl": "https://mdrnclassic.com/products/ultimate-grooming-elegance-trio",
  "featured": false,
  "order": 12
}
